[
  {
    "fixture": {
      "id": 21250818,
      "date": "2025-08-18T18:00:00.000Z",
      "status": {
        "long": "Not Started",
        "short": "NS"
      },
      "venue": {
        "name": "Vila Belmiro"
      }
    },
    "league": {
      "id": 71,
      "name": "Serie A",
      "logo": "https://media.api-sports.io/football/leagues/71.png",
      "round": "Regular Season - 20"
    },
    "teams": {
      "home": {
        "id": 1207,
        "name": "RB Bragantino",
        "logo": "https://media.api-sports.io/football/teams/1207.png"
      },
      "away": {
        "id": 125,
        "name": "Fluminense",
        "logo": "https://media.api-sports.io/football/teams/125.png"
      }
    },
    "goals": {
      "home": null,
      "away": null
    }
  }
]